MANIFEST.in
pyrad.py
rad.py
setup.py
images/Wikimedia_Flattr_Button.png
pyRadKDE.egg-info/PKG-INFO
pyRadKDE.egg-info/SOURCES.txt
pyRadKDE.egg-info/dependency_links.txt
pyRadKDE.egg-info/top_level.txt