Metadata-Version: 1.1
Name: pyRadKDE
Version: 0.7.1
Summary: a wheel type command interface for KDE, inspired by Kommando (KDE 3) and Neverwinternights.
Home-page: http://draketo.de/light/english/pyrad
Author: Arne Babenhauserheide
Author-email: arne_bab@web.de
License: GNU GPL-3 or later
Keywords: babtools
Platform: any
Classifier: License :: OSI Approved :: GNU General Public License (GPL)
Classifier: Programming Language :: Python
Classifier: Operating System :: OS Independent
Classifier: Intended Audience :: End Users/Desktop
Classifier: Environment :: X11 Applications :: KDE
Classifier: Development Status :: 4 - Beta
Requires: PyQt4
Requires: PyKDE4
